pycounts_toy_az/__init__.py
pycounts_toy_az/plotting.py
pycounts_toy_az/pycounts.py
pycounts_toy_az-0.1.0.dist-info/LICENSE
pycounts_toy_az-0.1.0.dist-info/METADATA
pycounts_toy_az-0.1.0.dist-info/WHEEL
pycounts_toy_az-0.1.0.dist-info/RECORD
