Metadata-Version: 2.1
Name: pycounts_toy_az
Version: 0.1.0
Summary: A toy package for counting words in a text file. DSCI524 individual assignment
License: MIT
Author: Alix Zhou
Requires-Python: >=3.9
Classifier: License :: OSI Approved :: MIT License
Classifier: Programming Language :: Python :: 3
Classifier: Programming Language :: Python :: 3.9
Classifier: Programming Language :: Python :: 3.10
Classifier: Programming Language :: Python :: 3.11
Classifier: Programming Language :: Python :: 3.12
Classifier: Programming Language :: Python :: 3.13
Requires-Dist: matplotlib (>=3.4.3)
